openapi_description_generator/__init__.py
openapi_description_generator-3.1.1.4.dist-info/LICENSE
openapi_description_generator-3.1.1.4.dist-info/METADATA
openapi_description_generator-3.1.1.4.dist-info/WHEEL
openapi_description_generator-3.1.1.4.dist-info/top_level.txt
openapi_description_generator-3.1.1.4.dist-info/RECORD
