Metadata-Version: 2.2
Name: openapi-description-generator
Version: 3.1.1.4
Summary: A framework agnostic library to generate openapi description files
Author-email: Michael <michael.smith.ok@gmail.com>
Project-URL: Homepage, https://github.com/smwa/openapi_description_generator
Project-URL: Issues, https://github.com/smwa/openapi_description_generator/issues
Classifier: Programming Language :: Python :: 3
Classifier: Operating System :: OS Independent
Requires-Python: >=3.10
License-File: LICENSE
Requires-Dist: dataclasses-json
Requires-Dist: PyYAML
